{
    "video": {
        "id": "Pktno_n6IL4",
        "channel": "youtube"
    },
    "text": "Are you searching for beautiful wedding venues near you? Welcome to Mone Reve, the #1 event space for special occasions in New York. Our beautiful and purpose-built event venue will bring life to your event and make it memorable for you and your guests.",
    "services": [{
            "id": "01",
            "title": "Weddings"
        },
        {
            "id": "02",
            "title": "Anniversaries"
        },
        {
            "id": "03",
            "title": "Birthdays Parties"
        },
        {
            "id": "04",
            "title": "Coporate Events"
        }
    ]
}